{"verts": [[0.11, 0.1], [0.1, 0.11], [0.1, 5.62], [9.06, 5.62], [9.06, 3.63], [9.07, 3.62], [9.17, 3.62], [9.18, 3.63], [9.17, 3.64], [9.17, 3.67], [9.18, 3.68], [9.18, 5.62], [13.83, 5.62], [13.83, 0.1], [9.17, 0.1], [9.18, 0.11], [9.18, 2.63], [9.17, 2.64], [9.07, 2.64], [9.06, 2.63], [9.06, 0.1]], "id": "793e0ed215c6f9e18b36a5e4bccef7fd", "room_category": {"Bedroom": [[-0.02, -0.05, 9.16, 6.37]], "Toilet": [[9.03, -0.02, 13.97, 5.73]], "Bathroom": [[9.03, -0.02, 13.97, 5.73]]}, "room_num": 2, "bbox": {"min": [0.1, 0.1], "max": [13.83, 5.62]}}