{"verts": [[0.11, 0.1], [0.1, 0.11], [0.1, 6.7], [2.54, 6.7], [2.55, 6.71], [2.55, 6.81], [2.54, 6.82], [0.12, 6.82], [0.12, 11.8], [5.9, 11.8], [5.9, 9.32], [5.91, 9.31], [5.91, 9.16], [5.92, 9.15], [5.92, 6.82], [4.53, 6.82], [4.52, 6.81], [4.52, 6.71], [4.53, 6.7], [6.02, 6.7], [6.05, 6.73], [6.05, 9.04], [10.55, 9.04], [10.55, 0.1]], "id": "e19db5b80f39d9abe618e3b9a14cdf9d", "room_category": {"Kitchen": [[-0.01, 6.69, 6.02, 11.93]], "Living_Room": [[-0.03, -0.76, 10.68, 9.15]], "Dining_Room": [[-0.03, -0.76, 10.68, 9.15]]}, "room_num": 2, "bbox": {"min": [0.1, 0.1], "max": [10.55, 11.8]}}